baltrack/__init__.py
baltrack/__main__.py
baltrack/_web3.py
baltrack/alembic.ini
baltrack/base.py
baltrack/mem.py
baltrack/utils.py
baltrack/migrations/README
baltrack/migrations/env.py
baltrack/migrations/script.py.mako
baltrack/migrations/versions/e982668f2bbe_initial_schema.py
baltrack/sql/__init__.py
baltrack/sql/model.py
baltrack-0.3.0.dist-info/entry_points.txt
baltrack-0.3.0.dist-info/WHEEL
baltrack-0.3.0.dist-info/METADATA
baltrack-0.3.0.dist-info/RECORD
