Metadata-Version: 2.4
Name: baltrack
Version: 0.3.0
Summary: baltrack tracks ERC20 token balances.
Author-email: Eugene Kim <ab@astral.blue>
Requires-Python: >=3.12
License-Expression: MIT
Requires-Dist: web3>=7.10.0
Requires-Dist: eth-typing>=5.2.1
Requires-Dist: evmchains>=0.1.4
Requires-Dist: structlog>=25.2.0
Requires-Dist: sqlalchemy[asyncio, postgresql-asyncpg]>=2.0.40
Requires-Dist: alembic[tz]>=1.15.2
Requires-Dist: asyncpg>=0.30.0
Requires-Dist: python-dotenv>=1.1.0
Requires-Dist: pytest>=8.3.5 ; extra == "dev"
Requires-Dist: pytest-cov>=6.1.1 ; extra == "dev"
Requires-Dist: isort>=6.0.1 ; extra == "dev"
Requires-Dist: black>=25.1.0 ; extra == "dev"
Requires-Dist: autopep8>=2.3.2 ; extra == "dev"
Requires-Dist: sphinx>=8.2.3 ; extra == "dev"
Project-URL: Home, https://github.com/astralblue/baltrack
Provides-Extra: dev
